syncto/__init__.py
syncto/authentication.py
syncto/crypto.py
syncto/headers.py
syncto/heartbeat.py
syncto/tests/__init__.py
syncto/tests/support.py
syncto/tests/test_authentication.py
syncto/tests/test_crypto.py
syncto/tests/test_functional.py
syncto/tests/test_statsd.py
syncto/views/__init__.py
syncto/views/collection.py
syncto/views/errors.py
syncto/views/record.py
syncto-1.5.0.dist-info/DESCRIPTION.rst
syncto-1.5.0.dist-info/METADATA
syncto-1.5.0.dist-info/RECORD
syncto-1.5.0.dist-info/WHEEL
syncto-1.5.0.dist-info/entry_points.txt
syncto-1.5.0.dist-info/metadata.json
syncto-1.5.0.dist-info/pbr.json
syncto-1.5.0.dist-info/top_level.txt
