Metadata-Version: 2.0
Name: syncto
Version: 1.5.0
Summary: Read Firefox Sync server using Kinto API.
Home-page: https://syncto.readthedocs.org/
Author: Mozilla Services
Author-email: services-dev@mozilla.com
License: Apache License (2.0)
Keywords: web services
Platform: UNKNOWN
Classifier: Programming Language :: Python
Classifier: Programming Language :: Python :: 2.7
Classifier: Programming Language :: Python :: 3.4
Classifier: Programming Language :: Python :: 3.5
Classifier: Programming Language :: Python :: Implementation :: CPython
Classifier: Topic :: Internet :: WWW/HTTP
Classifier: Topic :: Internet :: WWW/HTTP :: WSGI :: Application
Classifier: License :: OSI Approved :: Apache Software License
Requires-Dist: PyNaCl (>=1.0,<1.1)
Requires-Dist: cliquet[monitoring] (>=2.15,<2.16)
Requires-Dist: hkdf (==0.0.3)
Requires-Dist: ndg-httpsclient
Requires-Dist: pyasn1
Requires-Dist: pyopenssl
Requires-Dist: syncclient (>=0.8,<0.9)
Requires-Dist: waitress (>=0.8,<0.9)
